opendp/smartnoise/__init__.py
opendp/smartnoise/show_deprecated.py
opendp/smartnoise/core/__init__.py
opendp/smartnoise/core/api.py
opendp/smartnoise/core/api_pb2.py
opendp/smartnoise/core/base.py
opendp/smartnoise/core/base_pb2.py
opendp/smartnoise/core/components.py
opendp/smartnoise/core/components_pb2.py
opendp/smartnoise/core/value.py
opendp/smartnoise/core/value_pb2.py
opendp/smartnoise/core/variant_message_map.py
opendp_smartnoise_core-0.2.6.dist-info/LICENSE
opendp_smartnoise_core-0.2.6.dist-info/METADATA
opendp_smartnoise_core-0.2.6.dist-info/WHEEL
opendp_smartnoise_core-0.2.6.dist-info/top_level.txt
opendp_smartnoise_core-0.2.6.dist-info/RECORD
