Metadata-Version: 2.1
Name: opendp-smartnoise-core
Version: 0.2.6
Summary: Deprecated. Please use the OpenDP library: https://github.com/opendp/opendp
Home-page: https://github.com/opendp/smartnoise-core-python
Author: Consequences of Data
Author-email: info@opendp.org
Keywords: differential-privacy
Platform: any
Classifier: Development Status :: 7 - Inactive
Classifier: Intended Audience :: Developers
Classifier: Intended Audience :: Science/Research
Classifier: Operating System :: MacOS
Classifier: Operating System :: Microsoft :: Windows
Classifier: Operating System :: POSIX :: Linux
Classifier: Natural Language :: English
Classifier: Programming Language :: Python
Classifier: Programming Language :: Python :: 3
Classifier: Programming Language :: Python :: 3.6
Classifier: Programming Language :: Python :: 3.7
Classifier: Programming Language :: Python :: 3.8
Classifier: Programming Language :: Python :: 3.9
Classifier: Topic :: Scientific/Engineering
Requires-Python: >=3.6
License-File: LICENSE
